kuva_reader/__init__.py
kuva_reader/py.typed
kuva_reader/reader/__init__.py
kuva_reader/reader/image.py
kuva_reader/reader/level0.py
kuva_reader/reader/level1.py
kuva_reader/reader/level2.py
kuva_reader/reader/product_base.py
kuva_reader/reader/py.typed
kuva_reader/reader/read.py
kuva_reader/reader/utils.py
kuva_reader-1.1.7.dist-info/METADATA
kuva_reader-1.1.7.dist-info/WHEEL
kuva_reader-1.1.7.dist-info/entry_points.txt
kuva_reader-1.1.7.dist-info/RECORD
