Metadata-Version: 2.4
Name: kuva-reader
Version: 1.1.7
Summary: Manipulate the Kuva Space image and metadata formats
Author-email: Guillem Ballesteros <guillem@kuvaspace.com>, Lennert Antson <lennert.antson@kuvaspace.com>, Arthur Vandenhoeke <arthur.vandenhoeke@kuvaspace.com>, Olli Eloranta <olli.eloranta@kuvaspace.com>
License-Expression: MIT
Requires-Python: <=3.13,>=3.10
Requires-Dist: kuva-geometry<2.0.0,>=1.0.1
Requires-Dist: kuva-metadata<2.0.0,>=1.1.1
Requires-Dist: numpy-quaternion>=2023.4.4
Requires-Dist: numpy>=1.26.4
Requires-Dist: pint<1.0.0,>=0.22
Requires-Dist: rasterio<2,>=1.4.3
